{
    "species": "moltres",
    "nickname": "TOASTY",
    "level": 100,
    "ability": "pressure",
    "moves": [
        "hurricane",
        "endure",
        "overheat",
        "sky-attack"
    ],
    "ivs": {
        "hp": 2,
        "attack": 9,
        "defence": 8,
        "special_attack": 17,
        "special_defence": 29,
        "speed": 14
    },
    "evs": {
        "hp": 6,
        "attack": 4,
        "defence": 6,
        "special_attack": 10,
        "special_defence": 4,
        "speed": 8
    },
    "nature": "Brave",
    "original_trainer": "ARCHIE",
    "experience": 1250000,
    "caught_ball": "COBBLEMON:MASTER_BALL",
    "gender": "GENDERLESS",
    "friendship": 35,
    "shiny": 1,
    "met_level": 100,
    "met_location": "30001",
    "met_date": "2022-5-20",
    "tid": 14666,
    "pid": 1228072327,
    "sid": 38395,
    "language": 2,
    "origin_game": "HG",
    "is_egg": false,
    "tera_type": "Fire",
    "home_tracker": 6998364137756136194,
    "encryption_constant": 1228072327,
    "height": 176,
    "weight": 131,
    "scale": 176,
    "ribbons": [],
    "relearn_flags": [
        false,
        false,
        false,
        false,
        false,
        false,
        false,
        false,
        false,
        false,
        false,
        false,
        false,
        false,
        false,
        false,
        false,
        false,
        false,
        false,
        false,
        false,
        false,
        false,
        false,
        false,
        false,
        false,
        false,
        false,
        false,
        false,
        false,
        false,
        false,
        false,
        false,
        false,
        false,
        false,
        false,
        false,
        false,
        false,
        false,
        false,
        false,
        false,
        false,
        false,
        false,
        false,
        false,
        false,
        false,
        false,
        false,
        false,
        false,
        false,
        false,
        false,
        false,
        false,
        false,
        false,
        false,
        false,
        false,
        false,
        false,
        false,
        false,
        false,
        false,
        false,
        false,
        false,
        false,
        false,
        false,
        false,
        false,
        false,
        false,
        false,
        false,
        false,
        false,
        false,
        false,
        false,
        false,
        false,
        false,
        false,
        false,
        false,
        false,
        false,
        false,
        false,
        false,
        false,
        false,
        false,
        false,
        false,
        false,
        false,
        false,
        false,
        false,
        false,
        false,
        false,
        false,
        false,
        false,
        false,
        false,
        false,
        false,
        false,
        false,
        false,
        false,
        false,
        false,
        false,
        false,
        false,
        false,
        false,
        false,
        false,
        false,
        false,
        false,
        false,
        false,
        false,
        false,
        false,
        false,
        false,
        false,
        false,
        false,
        false,
        false,
        false,
        false,
        false,
        false,
        false,
        false,
        false,
        false,
        false,
        false,
        false,
        false,
        false,
        false,
        false,
        false,
        false,
        false,
        false,
        false,
        false,
        false,
        false,
        false,
        false,
        false,
        false,
        false,
        false,
        false,
        false,
        false,
        false,
        false,
        false,
        false,
        false,
        false,
        false,
        false,
        false,
        false,
        false,
        false,
        false,
        false,
        false,
        false,
        false,
        false,
        false,
        false,
        false,
        false,
        false,
        false,
        false,
        false,
        false,
        false,
        false,
        false,
        false,
        false,
        false,
        false,
        false,
        false,
        false,
        false,
        false,
        false,
        false,
        false,
        false,
        false,
        false,
        false,
        false,
        false,
        false,
        false,
        false,
        false,
        false,
        false,
        false,
        false,
        false,
        false,
        false,
        false,
        false,
        false,
        false,
        false,
        false,
        false,
        false,
        false,
        false,
        false,
        false,
        false,
        false,
        false,
        false,
        false,
        false,
        false,
        false,
        false,
        false,
        false,
        false,
        false,
        false,
        false,
        false,
        false,
        false,
        false,
        false,
        false,
        false,
        false,
        false,
        false,
        false,
        false,
        false,
        false,
        false,
        false,
        false,
        false,
        false,
        false,
        false,
        false,
        false,
        false,
        false,
        false,
        false,
        false,
        false,
        false,
        false,
        false,
        false,
        false,
        false
    ],
    "fateful_encounter": false,
    "memories": {
        "memory_type": 0,
        "memory_intensity": 0,
        "memory_feeling": 0,
        "memory_variable": 0
    },
    "box_number": 1,
    "slot_number": 4
}