{
    "species": "pansear",
    "nickname": "FYREWYATT",
    "level": 63,
    "ability": "gluttony",
    "moves": [
        "crunch",
        "acrobatics",
        "yawn",
        "fire-blast"
    ],
    "ivs": {
        "hp": 27,
        "attack": 1,
        "defence": 21,
        "special_attack": 17,
        "special_defence": 7,
        "speed": 23
    },
    "evs": {
        "hp": 32,
        "attack": 220,
        "defence": 37,
        "special_attack": 40,
        "special_defence": 19,
        "speed": 134
    },
    "nature": "Timid",
    "original_trainer": "ARCHIE",
    "experience": 257676,
    "caught_ball": "COBBLEMON:POKE_BALL",
    "gender": "FEMALE",
    "friendship": 255,
    "shiny": 0,
    "met_level": 10,
    "met_location": "32",
    "met_date": "2023-6-17",
    "tid": 15021,
    "pid": 3877293082,
    "sid": 44153,
    "language": 2,
    "origin_game": "B",
    "is_egg": false,
    "tera_type": "Normal",
    "home_tracker": 0,
    "encryption_constant": 3877293082,
    "height": 0,
    "weight": 0,
    "scale": 0,
    "ribbons": [],
    "relearn_flags": [
        false,
        false,
        false,
        false,
        false,
        false,
        false,
        false,
        false,
        false,
        false,
        false,
        false,
        false,
        false,
        false,
        false,
        false,
        false,
        false,
        false,
        false,
        false,
        false,
        false,
        false,
        false,
        false,
        false,
        false,
        false,
        false,
        false,
        false,
        false,
        false,
        false,
        false,
        false,
        false,
        false,
        false,
        false,
        false,
        false,
        false,
        false,
        false,
        false,
        false,
        false,
        false,
        false,
        false,
        false,
        false,
        false,
        false,
        false,
        false,
        false,
        false,
        false,
        false,
        false,
        false,
        false,
        false,
        false,
        false,
        false,
        false,
        false,
        false,
        false,
        false,
        false,
        false,
        false,
        false,
        false,
        false,
        false,
        false,
        false,
        false,
        false,
        false,
        false,
        false,
        false,
        false,
        false,
        false,
        false,
        false,
        false,
        false,
        false,
        false,
        false,
        false,
        false,
        false,
        false,
        false,
        false,
        false,
        false,
        false,
        false,
        false,
        false,
        false,
        false,
        false,
        false,
        false,
        false,
        false,
        false,
        false,
        false,
        false,
        false,
        false,
        false,
        false,
        false,
        false,
        false,
        false,
        false,
        false,
        false,
        false,
        false,
        false,
        false,
        false,
        false,
        false,
        false,
        false,
        false,
        false,
        false,
        false,
        false,
        false,
        false,
        false,
        false,
        false,
        false,
        false,
        false,
        false,
        false,
        false,
        false,
        false,
        false,
        false,
        false,
        false,
        false,
        false,
        false,
        false,
        false,
        false,
        false,
        false,
        false,
        false,
        false,
        false,
        false,
        false,
        false,
        false,
        false,
        false,
        false,
        false,
        false,
        false,
        false,
        false,
        false,
        false,
        false,
        false,
        false,
        false,
        false,
        false,
        false,
        false,
        false,
        false,
        false,
        false,
        false,
        false,
        false,
        false,
        false,
        false,
        false,
        false,
        false,
        false,
        false,
        false,
        false,
        false,
        false,
        false,
        false,
        false,
        false,
        false,
        false,
        false,
        false,
        false,
        false,
        false,
        false,
        false,
        false,
        false,
        false,
        false,
        false,
        false,
        false,
        false,
        false,
        false,
        false,
        false,
        false,
        false,
        false,
        false,
        false,
        false,
        false,
        false,
        false,
        false,
        false,
        false,
        false,
        false,
        false,
        false,
        false,
        false,
        false,
        false,
        false,
        false,
        false,
        false,
        false,
        false,
        false,
        false,
        false,
        false,
        false,
        false,
        false,
        false,
        false,
        false,
        false,
        false,
        false,
        false,
        false,
        false,
        false,
        false,
        false,
        false,
        false,
        false,
        false,
        false,
        false,
        false,
        false,
        false,
        false,
        false,
        false,
        false,
        false,
        false
    ],
    "fateful_encounter": false,
    "memories": {
        "memory_type": 0,
        "memory_intensity": 0,
        "memory_feeling": 0,
        "memory_variable": 0
    },
    "box_number": 1,
    "slot_number": 26
}