{
    "species": "bisharp",
    "nickname": "Bisharp",
    "level": 23,
    "ability": "Inner-focus",
    "moves": [
        "scary-face",
        "feint-attack",
        "torment",
        "scratch"
    ],
    "ivs": {
        "attack": 16,
        "defence": 8,
        "hp": 1,
        "special_attack": 18,
        "special_defence": 25,
        "speed": 27
    },
    "evs": {
        "attack": 0,
        "defence": 0,
        "hp": 0,
        "special_attack": 0,
        "special_defence": 0,
        "speed": 0
    },
    "nature": "Brave",
    "original_trainer": "MiniDuncan",
    "health": 36,
    "experience": 12167,
    "shiny": 0,
    "caught_ball": "cobblemon:ultra_ball",
    "gender": "MALE",
    "friendship": 50,
    "healing_timer": 60,
    "gmax_factor": 0,
    "gmax_level": 0,
    "tera_type": "cobblemon:rock",
    "form_id": "normal",
    "uuid": [
        1494023616,
        -1960687899,
        -1583939225,
        -1244292403
    ],
    "scale_modifier": 1.0,
    "met_date": "2025-04-14",
    "met_level": 23,
    "met_location": "a lovely place",
    "origin_game": "Cobblemon",
    "language": 2,
    "tid": null,
    "pid": null,
    "sid": null,
    "home_tracker": 0,
    "encryption_constant": 0,
    "height": 0,
    "weight": 0,
    "scale": 0,
    "ribbons": [],
    "relearn_flags": [],
    "fateful_encounter": false,
    "memories": {
        "memory_type": 0,
        "memory_intensity": 0,
        "memory_feeling": 0,
        "memory_variable": 0
    },
    "box_number": 5,
    "slot_number": 3
}