{
    "species": "minior",
    "nickname": "Minior",
    "level": 27,
    "ability": "Shields-down",
    "moves": [
        "stealth-rock",
        "self-destruct",
        "ancient-power",
        "swift"
    ],
    "ivs": {
        "attack": 14,
        "defence": 0,
        "hp": 8,
        "special_attack": 26,
        "special_defence": 18,
        "speed": 16
    },
    "evs": {
        "attack": 0,
        "defence": 0,
        "hp": 0,
        "special_attack": 0,
        "special_defence": 0,
        "speed": 0
    },
    "nature": "Mild",
    "original_trainer": "MiniDuncan",
    "health": 71,
    "experience": 15244,
    "shiny": 0,
    "caught_ball": "cobblemon:ancient_jet_ball",
    "gender": "GENDERLESS",
    "friendship": 50,
    "healing_timer": 60,
    "gmax_factor": 0,
    "gmax_level": 0,
    "tera_type": "cobblemon:flying",
    "form_id": "normal",
    "uuid": [
        598894399,
        -1689894533,
        -1818683741,
        -1429959974
    ],
    "scale_modifier": 1.0,
    "met_date": "2025-04-14",
    "met_level": 27,
    "met_location": "a lovely place",
    "origin_game": "Cobblemon",
    "language": 2,
    "tid": null,
    "pid": null,
    "sid": null,
    "home_tracker": 0,
    "encryption_constant": 0,
    "height": 0,
    "weight": 0,
    "scale": 0,
    "ribbons": [],
    "relearn_flags": [],
    "fateful_encounter": false,
    "memories": {
        "memory_type": 0,
        "memory_intensity": 0,
        "memory_feeling": 0,
        "memory_variable": 0
    },
    "box_number": 3,
    "slot_number": 11
}