{
    "species": "sneasel",
    "nickname": "Sneasel",
    "level": 58,
    "ability": "inner-focus",
    "moves": [
        "hone-claws",
        "beat-up",
        "agility",
        "screech"
    ],
    "ivs": {
        "hp": 11,
        "attack": 14,
        "defence": 22,
        "special_attack": 14,
        "special_defence": 19,
        "speed": 27
    },
    "evs": {
        "hp": 0,
        "attack": 0,
        "defence": 0,
        "special_attack": 0,
        "special_defence": 0,
        "speed": 0
    },
    "nature": "Brave",
    "original_trainer": "ARCHIE",
    "experience": 189334,
    "caught_ball": "COBBLEMON:ULTRA_BALL",
    "gender": "FEMALE",
    "friendship": 35,
    "shiny": 0,
    "met_level": 58,
    "met_location": "61",
    "met_date": "2025-3-16",
    "tid": 15021,
    "pid": 1095774506,
    "sid": 44153,
    "language": 2,
    "origin_game": "B",
    "is_egg": false,
    "tera_type": "Dark",
    "home_tracker": 0,
    "encryption_constant": 1095774506,
    "height": 47,
    "weight": 199,
    "scale": 47,
    "ribbons": [],
    "relearn_flags": [
        false,
        false,
        false,
        false,
        false,
        false,
        false,
        false,
        false,
        false,
        false,
        false,
        false,
        false,
        false,
        false,
        false,
        false,
        false,
        false,
        false,
        false,
        false,
        false,
        false,
        false,
        false,
        false,
        false,
        false,
        false,
        false,
        false,
        false,
        false,
        false,
        false,
        false,
        false,
        false,
        false,
        false,
        false,
        false,
        false,
        false,
        false,
        false,
        false,
        false,
        false,
        false,
        false,
        false,
        false,
        false,
        false,
        false,
        false,
        false,
        false,
        false,
        false,
        false,
        false,
        false,
        false,
        false,
        false,
        false,
        false,
        false,
        false,
        false,
        false,
        false,
        false,
        false,
        false,
        false,
        false,
        false,
        false,
        false,
        false,
        false,
        false,
        false,
        false,
        false,
        false,
        false,
        false,
        false,
        false,
        false,
        false,
        false,
        false,
        false,
        false,
        false,
        false,
        false,
        false,
        false,
        false,
        false,
        false,
        false,
        false,
        false,
        false,
        false,
        false,
        false,
        false,
        false,
        false,
        false,
        false,
        false,
        false,
        false,
        false,
        false,
        false,
        false,
        false,
        false,
        false,
        false,
        false,
        false,
        false,
        false,
        false,
        false,
        false,
        false,
        false,
        false,
        false,
        false,
        false,
        false,
        false,
        false,
        false,
        false,
        false,
        false,
        false,
        false,
        false,
        false,
        false,
        false,
        false,
        false,
        false,
        false,
        false,
        false,
        false,
        false,
        false,
        false,
        false,
        false,
        false,
        false,
        false,
        false,
        false,
        false,
        false,
        false,
        false,
        false,
        false,
        false,
        false,
        false,
        false,
        false,
        false,
        false,
        false,
        false,
        false,
        false,
        false,
        false,
        false,
        false,
        false,
        false,
        false,
        false,
        false,
        false,
        false,
        false,
        false,
        false,
        false,
        false,
        false,
        false,
        false,
        false,
        false,
        false,
        false,
        false,
        false,
        false,
        false,
        false,
        false,
        false,
        false,
        false,
        false,
        false,
        false,
        false,
        false,
        false,
        false,
        false,
        false,
        false,
        false,
        false,
        false,
        false,
        false,
        false,
        false,
        false,
        false,
        false,
        false,
        false,
        false,
        false,
        false,
        false,
        false,
        false,
        false,
        false,
        false,
        false,
        false,
        false,
        false,
        false,
        false,
        false,
        false,
        false,
        false,
        false,
        false,
        false,
        false,
        false,
        false,
        false,
        false,
        false,
        false,
        false,
        false,
        false,
        false,
        false,
        false,
        false,
        false,
        false,
        false,
        false,
        false,
        false,
        false,
        false,
        false,
        false,
        false,
        false,
        false,
        false,
        false,
        false,
        false,
        false,
        false,
        false,
        false,
        false
    ],
    "fateful_encounter": false,
    "memories": {
        "memory_type": 0,
        "memory_intensity": 0,
        "memory_feeling": 0,
        "memory_variable": 0
    },
    "box_number": 1,
    "slot_number": 9
}